invariants_py/__init__.py
invariants_py/collision_detection_bottle.py
invariants_py/data_handler.py
invariants_py/dynamics_screw_invariants.py
invariants_py/dynamics_vector_invariants.py
invariants_py/initialization.py
invariants_py/invariants_handler.py
invariants_py/ocp_helper.py
invariants_py/reparameterization.py
invariants_py/spline_handler.py
invariants_py/tutorial_scripts.py
invariants_py/calculate_invariants/README.md
invariants_py/calculate_invariants/__init__.py
invariants_py/calculate_invariants/opti_calculate_screw_invariants_pose.py
invariants_py/calculate_invariants/opti_calculate_vector_invariants_position.py
invariants_py/calculate_invariants/opti_calculate_vector_invariants_position_mf.py
invariants_py/calculate_invariants/opti_calculate_vector_invariants_position_mj.py
invariants_py/calculate_invariants/opti_calculate_vector_invariants_rotation.py
invariants_py/calculate_invariants/rockit_calculate_vector_invariants_position.py
invariants_py/calculate_invariants/rockit_calculate_vector_invariants_position_mf.py
invariants_py/calculate_invariants/rockit_calculate_vector_invariants_position_mj.py
invariants_py/calculate_invariants/rockit_calculate_vector_invariants_rotation.py
invariants_py/data/__init__.py
invariants_py/data/beer_1.txt
invariants_py/data/bottle.stl
invariants_py/data/contour_coordinates.out
invariants_py/data/curved_motion.csv
invariants_py/data/inv_model.pkl
invariants_py/data/kettle.obj
invariants_py/data/opener.stl
invariants_py/data/pouring_motion.csv
invariants_py/data/pouring_segmentation.csv
invariants_py/data/recorded_motion.csv
invariants_py/data/scooping_motion.csv
invariants_py/data/sine_wave.txt
invariants_py/data/sine_wave_invariant_model.csv
invariants_py/data/single_pose.csv
invariants_py/data/trajectory_long.csv
invariants_py/data/robot/ur10.urdf
invariants_py/external/GJK/compute_distance.py
invariants_py/external/GJK/geometry.py
invariants_py/generate_trajectory/__init__.py
invariants_py-0.3.9.dist-info/METADATA
invariants_py-0.3.9.dist-info/WHEEL
invariants_py-0.3.9.dist-info/licenses/LICENSE
invariants_py-0.3.9.dist-info/RECORD
